aquadb/__init__.py
aquadb/configurator.py
aquadb/connection.py
aquadb/executor.py
aquadb/ocl.ini
aquadb/parser.py
aquadb/query.py
aquadb-1.1.1.dist-info/LICENSE
aquadb-1.1.1.dist-info/METADATA
aquadb-1.1.1.dist-info/WHEEL
aquadb-1.1.1.dist-info/top_level.txt
aquadb-1.1.1.dist-info/RECORD
